meraki_syslog_parser/README_mac.md
meraki_syslog_parser/__init__.py
meraki_syslog_parser/main.py
meraki_syslog_parser/meraki_mx_syslog_parser.py
meraki_syslog_parser/randomize_mac.py
meraki_syslog_parser/requirements.txt
meraki_syslog_parser/samples/meraki_events_mac_rand.log
meraki_syslog_parser/samples/meraki_firewall_mac_rand.log
meraki_syslog_parser/samples/meraki_urls_mac_rand.log
meraki_syslog_parser-0.1.0.dist-info/LICENSE
meraki_syslog_parser-0.1.0.dist-info/METADATA
meraki_syslog_parser-0.1.0.dist-info/WHEEL
meraki_syslog_parser-0.1.0.dist-info/RECORD
